phyto_nas_tsc/__init__.py
phyto_nas_tsc/_config.py
phyto_nas_tsc/_data_handler.py
phyto_nas_tsc/_evolutionary_algorithm.py
phyto_nas_tsc/_model_builder.py
phyto_nas_tsc/_optimizer.py
phyto_nas_tsc/_utils.py
phyto_nas_tsc/core.py
phyto_nas_tsc/version.py
phyto_nas_tsc/data/X_test.csv
phyto_nas_tsc/data/X_train.csv
phyto_nas_tsc/data/y_test.csv
phyto_nas_tsc/data/y_train.csv
tests/__init__.py
tests/conftest.py
tests/test_core.py
tests/test_data_handler.py
tests/test_evolutionary_algorithm.py
tests/test_model_builder.py
tests/test_utils.py
phyto_nas_tsc-0.1.6.dist-info/METADATA
phyto_nas_tsc-0.1.6.dist-info/WHEEL
phyto_nas_tsc-0.1.6.dist-info/top_level.txt
phyto_nas_tsc-0.1.6.dist-info/RECORD
